ipfabric/__init__.py
ipfabric/api.py
ipfabric/auth.py
ipfabric/client.py
ipfabric/diagrams/__init__.py
ipfabric/diagrams/graphs.py
ipfabric/diagrams/icmp.py
ipfabric/diagrams/input_models/__init__.py
ipfabric/diagrams/input_models/constants.py
ipfabric/diagrams/input_models/factory_defaults/__init__.py
ipfabric/diagrams/input_models/factory_defaults/networkSettings.json
ipfabric/diagrams/input_models/factory_defaults/pathLookupSettings.json
ipfabric/diagrams/input_models/graph_parameters.py
ipfabric/diagrams/input_models/graph_settings.py
ipfabric/diagrams/input_models/shared_view.py
ipfabric/diagrams/output_models/__init__.py
ipfabric/diagrams/output_models/graph_result.py
ipfabric/diagrams/output_models/protocols.py
ipfabric/diagrams/output_models/trace.py
ipfabric/dynamic_attributes/__init__.py
ipfabric/dynamic_attributes/configs/__init__.py
ipfabric/dynamic_attributes/configs/filters.py
ipfabric/dynamic_attributes/configs/rules.py
ipfabric/dynamic_attributes/configs/sync.py
ipfabric/dynamic_attributes/configs/values.py
ipfabric/dynamic_attributes/models.py
ipfabric/dynamic_attributes/sync.py
ipfabric/models/__init__.py
ipfabric/models/authentication.py
ipfabric/models/config_export.py
ipfabric/models/device.py
ipfabric/models/discovery.py
ipfabric/models/extensions.py
ipfabric/models/global_search.py
ipfabric/models/intent.py
ipfabric/models/intent_check.py
ipfabric/models/inventory.py
ipfabric/models/jobs.py
ipfabric/models/matrix.py
ipfabric/models/oas.py
ipfabric/models/rbac.py
ipfabric/models/security.py
ipfabric/models/site_separation.py
ipfabric/models/snapshot.py
ipfabric/models/snapshots.py
ipfabric/models/table.py
ipfabric/models/technology/__init__.py
ipfabric/models/technology/addressing.py
ipfabric/models/technology/cloud.py
ipfabric/models/technology/dhcp.py
ipfabric/models/technology/fhrp.py
ipfabric/models/technology/interfaces.py
ipfabric/models/technology/ip_telephony.py
ipfabric/models/technology/load_balancing.py
ipfabric-7.9.0.dist-info/METADATA
ipfabric-7.9.0.dist-info/WHEEL
ipfabric-7.9.0.dist-info/entry_points.txt
ipfabric-7.9.0.dist-info/licenses/LICENSE
ipfabric-7.9.0.dist-info/licenses/NOTICES.md
ipfabric-7.9.0.dist-info/RECORD
