Metadata-Version: 2.4
Name: ipfabric
Version: 7.9.0
Summary: Python package for interacting with IP Fabric
License: MIT
License-File: LICENSE
License-File: NOTICES.md
Keywords: ipfabric,ip-fabric,community-fabric
Author: Solution Architecture
Author-email: solution.architecture@ipfabric.io
Requires-Python: >=3.9,<4.0
Classifier: License :: OSI Approved :: MIT License
Classifier: Programming Language :: Python :: 3
Classifier: Programming Language :: Python :: 3.9
Classifier: Programming Language :: Python :: 3.10
Classifier: Programming Language :: Python :: 3.11
Classifier: Programming Language :: Python :: 3.12
Classifier: Programming Language :: Python :: 3.13
Classifier: Programming Language :: Python :: 3.14
Provides-Extra: all
Provides-Extra: cli
Provides-Extra: cve
Provides-Extra: dynamic-attributes
Provides-Extra: examples
Provides-Extra: matrix
Provides-Extra: pd
Provides-Extra: webhook
Requires-Dist: case-insensitive-dictionary (>=0.2.1,<0.3.0)
Requires-Dist: deepdiff (>=8.0.0,<9.0.0)
Requires-Dist: fastapi (>=0.121.2,<0.122.0) ; extra == "webhook" or extra == "all"
Requires-Dist: jinja2 (>=3.1.4,<4.0.0) ; extra == "matrix" or extra == "all"
Requires-Dist: macaddress (>=2.0.2,<2.1.0)
Requires-Dist: niquests (>=3.16.0,<4.0.0)
Requires-Dist: openpyxl (>=3.1.2,<4.0.0) ; extra == "cve" or extra == "matrix" or extra == "cli" or extra == "examples" or extra == "dynamic-attributes" or extra == "all"
Requires-Dist: packaging (>=24.2,<26.0)
Requires-Dist: pandas (>=2.1.4,<3.0.0) ; extra == "cve" or extra == "matrix" or extra == "cli" or extra == "examples" or extra == "pd" or extra == "all"
Requires-Dist: pydantic (>=2.0.0,<3.0.0,!=2.11.0,!=2.11.1)
Requires-Dist: pydantic-extra-types (>=2.3.0,<3.0.0)
Requires-Dist: pydantic-settings (>=2.1.0,<3.0.0)
Requires-Dist: pyjwt (>=2.9.0,<3.0.0)
Requires-Dist: python-dateutil (>=2.8.2,<3.0.0)
Requires-Dist: python-dotenv (>=1.0,<2.0)
Requires-Dist: python-json-logger (>=2.0.7,<3.0.0) ; extra == "examples" or extra == "all"
Requires-Dist: pytz (>=2024,<2026)
Requires-Dist: pyyaml (>=6.0.1,<7.0.0) ; extra == "examples" or extra == "dynamic-attributes" or extra == "all"
Requires-Dist: pyyaml-include (>=2.2,<3.0) ; extra == "dynamic-attributes" or extra == "all"
Requires-Dist: rich (>=13.7.0,<15.0) ; extra == "cli" or extra == "examples" or extra == "all"
Requires-Dist: sqlmodel (>=0.0.27,<0.0.28) ; extra == "webhook" or extra == "all"
Requires-Dist: tomli (>=2.0.0,<3.0.0) ; (python_version < "3.11") and (extra == "dynamic-attributes" or extra == "all")
Requires-Dist: uvicorn (>=0.38.0,<0.39.0) ; extra == "webhook" or extra == "all"
Project-URL: Changelog, https://gitlab.com/ip-fabric/integrations/python-ipfabric/-/blob/main/CHANGELOG.md
Project-URL: Homepage, https://gitlab.com/ip-fabric/integrations/python-ipfabric
Project-URL: IP Fabric, https://ipfabric.io/
Project-URL: Repository, https://gitlab.com/ip-fabric/integrations/python-ipfabric
